LICENSE
MANIFEST.in
README.md
package.json
setup.py
dash_react_flowing/DashReactFlowing.py
dash_react_flowing/__init__.py
dash_react_flowing/_imports_.py
dash_react_flowing/dash_react_flowing.min.js
dash_react_flowing/dash_react_flowing.min.js.map
dash_react_flowing/metadata.json
dash_react_flowing/package-info.json
dash_react_flowing.egg-info/PKG-INFO
dash_react_flowing.egg-info/SOURCES.txt
dash_react_flowing.egg-info/dependency_links.txt
dash_react_flowing.egg-info/top_level.txt