Metadata-Version: 2.1
Name: dash-react-flowing
Version: 0.0.2
Summary: react-flow built into a Dash component
Home-page: UNKNOWN
Author: Ben Cannell <bean.can.design@gmail.com>
License: GPL-3.0
Platform: UNKNOWN
Classifier: Framework :: Dash
License-File: LICENSE
